<annotation><folder>2014/cam1</folder><filename>OBSEA141220092015_01_01.jpg</filename><path>2014/cam1/OBSEA141220092015_01_01.jpg</path><source><database>Unknown</database></source><size><width>2048</width><height>1536</height><depth>3</depth></size><segmented>0</segmented><object><name>fish</name><pose>Unspecified</pose><truncated>0</truncated><difficult>0</difficult><bndbox><xmin>1135</xmin><ymin>747</ymin><xmax>1588</xmax><ymax>1048</ymax></bndbox></object><object><name>fish</name><pose>Unspecified</pose><truncated>0</truncated><difficult>0</difficult><bndbox><xmin>1162</xmin><ymin>231</ymin><xmax>1430</xmax><ymax>381</ymax></bndbox></object><object><name>fish</name><pose>Unspecified</pose><truncated>0</truncated><difficult>0</difficult><bndbox><xmin>793</xmin><ymin>537</ymin><xmax>1113</xmax><ymax>790</ymax></bndbox></object><object><name>fish</name><pose>Unspecified</pose><truncated>0</truncated><difficult>0</difficult><bndbox><xmin>628</xmin><ymin>111</ymin><xmax>828</xmax><ymax>317</ymax></bndbox></object><object><name>fish</name><pose>Unspecified</pose><truncated>0</truncated><difficult>0</difficult><bndbox><xmin>278</xmin><ymin>616</ymin><xmax>622</xmax><ymax>898</ymax></bndbox></object><object><name>fish</name><pose>Unspecified</pose><truncated>0</truncated><difficult>0</difficult><bndbox><xmin>65</xmin><ymin>431</ymin><xmax>417</xmax><ymax>680</ymax></bndbox></object><object><name>fish</name><pose>Unspecified</pose><truncated>0</truncated><difficult>0</difficult><bndbox><xmin>-439</xmin><ymin>593</ymin><xmax>223</xmax><ymax>930</ymax></bndbox></object><object><name>fish</name><pose>Unspecified</pose><truncated>0</truncated><difficult>0</difficult><bndbox><xmin>625</xmin><ymin>914</ymin><xmax>856</xmax><ymax>1017</ymax></bndbox></object><object><name>fish</name><pose>Unspecified</pose><truncated>0</truncated><difficult>0</difficult><bndbox><xmin>1135</xmin><ymin>747</ymin><xmax>1588</xmax><ymax>1048</ymax></bndbox></object><object><name>fish</name><pose>Unspecified</pose><truncated>0</truncated><difficult>0</difficult><bndbox><xmin>1162</xmin><ymin>231</ymin><xmax>1430</xmax><ymax>381</ymax></bndbox></object><object><name>fish</name><pose>Unspecified</pose><truncated>0</truncated><difficult>0</difficult><bndbox><xmin>793</xmin><ymin>537</ymin><xmax>1113</xmax><ymax>790</ymax></bndbox></object><object><name>fish</name><pose>Unspecified</pose><truncated>0</truncated><difficult>0</difficult><bndbox><xmin>628</xmin><ymin>111</ymin><xmax>828</xmax><ymax>317</ymax></bndbox></object><object><name>fish</name><pose>Unspecified</pose><truncated>0</truncated><difficult>0</difficult><bndbox><xmin>278</xmin><ymin>616</ymin><xmax>622</xmax><ymax>898</ymax></bndbox></object><object><name>fish</name><pose>Unspecified</pose><truncated>0</truncated><difficult>0</difficult><bndbox><xmin>65</xmin><ymin>431</ymin><xmax>417</xmax><ymax>680</ymax></bndbox></object><object><name>fish</name><pose>Unspecified</pose><truncated>0</truncated><difficult>0</difficult><bndbox><xmin>-439</xmin><ymin>593</ymin><xmax>223</xmax><ymax>930</ymax></bndbox></object><object><name>fish</name><pose>Unspecified</pose><truncated>0</truncated><difficult>0</difficult><bndbox><xmin>625</xmin><ymin>914</ymin><xmax>856</xmax><ymax>1017</ymax></bndbox></object></annotation>